ezmpi/__init__.py
ezmpi/parallel.py
ezmpi-0.1.0.dist-info/licenses/LICENSE
ezmpi-0.1.0.dist-info/METADATA
ezmpi-0.1.0.dist-info/WHEEL
ezmpi-0.1.0.dist-info/top_level.txt
ezmpi-0.1.0.dist-info/RECORD
