Metadata-Version: 2.4
Name: ezmpi
Version: 0.1.0
Summary: A simple MPI processing pool for Python
Author-email: Minas Karamanis <minaskar@gmail.com>
License: MIT
Project-URL: Homepage, https://github.com/minask/ezmpi
Project-URL: Repository, https://github.com/minask/ezmpi.git
Project-URL: Issues, https://github.com/minask/ezmpi/issues
Keywords: mpi,parallel,processing,pool,hpc
Classifier: Development Status :: 3 - Alpha
Classifier: Intended Audience :: Developers
Classifier: Intended Audience :: Science/Research
Classifier: License :: OSI Approved :: MIT License
Classifier: Operating System :: OS Independent
Classifier: Programming Language :: Python :: 3
Classifier: Programming Language :: Python :: 3.8
Classifier: Programming Language :: Python :: 3.9
Classifier: Programming Language :: Python :: 3.10
Classifier: Programming Language :: Python :: 3.11
Classifier: Programming Language :: Python :: 3.12
Classifier: Topic :: Scientific/Engineering
Classifier: Topic :: Software Development :: Libraries :: Python Modules
Requires-Python: >=3.8
License-File: LICENSE
Requires-Dist: mpi4py>=3.0.0
Provides-Extra: dill
Requires-Dist: dill>=0.3.0; extra == "dill"
Provides-Extra: dev
Requires-Dist: pytest>=7.0; extra == "dev"
Requires-Dist: pytest-mpi>=0.6; extra == "dev"
Requires-Dist: pytest-cov>=4.0; extra == "dev"
Requires-Dist: ruff>=0.1.0; extra == "dev"
Requires-Dist: black>=23.0; extra == "dev"
Requires-Dist: mypy>=1.0; extra == "dev"
Requires-Dist: isort>=5.0; extra == "dev"
Provides-Extra: test
Requires-Dist: pytest>=7.0; extra == "test"
Requires-Dist: pytest-mpi>=0.6; extra == "test"
Requires-Dist: pytest-cov>=4.0; extra == "test"
Requires-Dist: pytest-benchmark>=4.0; extra == "test"
Provides-Extra: docs
Requires-Dist: mkdocs>=1.5.0; extra == "docs"
Requires-Dist: mkdocs-material>=9.0.0; extra == "docs"
Requires-Dist: mkdocstrings[python]>=0.24.0; extra == "docs"
Requires-Dist: mkdocs-gen-files>=0.5.0; extra == "docs"
Requires-Dist: mkdocs-literate-nav>=0.6.0; extra == "docs"
Requires-Dist: mkdocs-section-index>=0.3.5; extra == "docs"
Provides-Extra: build
Requires-Dist: build>=1.0.0; extra == "build"
Requires-Dist: twine>=4.0.0; extra == "build"
Dynamic: license-file
